UpgradePipPkgs/__init__.py
UpgradePipPkgs/main.py
UpgradePipPkgs/app/__init__.py
UpgradePipPkgs/app/events.py
UpgradePipPkgs/app/loggers.py
UpgradePipPkgs/app/scripts/upgrade_all.ps1
UpgradePipPkgs/logs/.gitkeep
UpgradePipPkgs/scripts/upgrade_all.ps1
UpgradePipPkgs-0.4.1.dist-info/LICENSE
UpgradePipPkgs-0.4.1.dist-info/METADATA
UpgradePipPkgs-0.4.1.dist-info/WHEEL
UpgradePipPkgs-0.4.1.dist-info/entry_points.txt
UpgradePipPkgs-0.4.1.dist-info/top_level.txt
UpgradePipPkgs-0.4.1.dist-info/RECORD
