Metadata-Version: 2.1
Name: UpgradePipPkgs
Version: 0.4.1
Summary: Tool for upgrading all `pip` packages within a Python environment using just one command.
Home-page: https://github.com/schlopp96/UpgradePipPkgs
Author: schlopp96
Author-email: schloppdaddy@gmail.com
Keywords: upgrade,pip,pkgs,pkg,package,packages,update,python,install,modules,module,installation,manager,upgrades,updates
Classifier: Development Status :: 3 - Alpha
Classifier: Intended Audience :: End Users/Desktop
Classifier: Intended Audience :: Developers
Classifier: Topic :: Software Development :: Build Tools
Classifier: Topic :: Software Development :: Libraries :: Python Modules
Classifier: Topic :: System :: Archiving :: Packaging
Classifier: Environment :: Console 
Classifier: License :: OSI Approved :: GNU General Public License v3 (GPLv3)
Classifier: Operating System :: Microsoft :: Windows
Classifier: Programming Language :: Python :: 3
Classifier: Programming Language :: Python :: 3.9
Classifier: Programming Language :: Python :: 3.10
License-File: LICENSE
Requires-Dist: alive-progress (>=2.4.1)
Requires-Dist: PyLoadBar (==0.2.0)
Requires-Dist: setuptools (>=62.1.0)
